nonebot_plugin_docs/__init__.py
nonebot_plugin_docs/dist/404.html
nonebot_plugin_docs/dist/assets/css/styles.dfa7e775.css
nonebot_plugin_docs/dist/assets/js/005e674f.22a11c12.js
nonebot_plugin_docs/dist/assets/js/00c5a353.8c39a020.js
nonebot_plugin_docs/dist/assets/js/01c1b5db.49ea3b38.js
nonebot_plugin_docs/dist/assets/js/02d305b1.b2a354cd.js
nonebot_plugin_docs/dist/assets/js/04c25a18.f787d91f.js
nonebot_plugin_docs/dist/assets/js/05bb5d2e.f31d0922.js
nonebot_plugin_docs/dist/assets/js/06b58946.17c26f42.js
nonebot_plugin_docs/dist/assets/js/071ceefa.945503cd.js
nonebot_plugin_docs/dist/assets/js/0813200e.b5cbdf52.js
nonebot_plugin_docs/dist/assets/js/0826a215.528c357d.js
nonebot_plugin_docs/dist/assets/js/09142b9d.c69b65d3.js
nonebot_plugin_docs/dist/assets/js/097fb44d.1f5235c0.js
nonebot_plugin_docs/dist/assets/js/0a69fddb.546d4b8d.js
nonebot_plugin_docs/dist/assets/js/0a899657.cfdc364c.js
nonebot_plugin_docs/dist/assets/js/0a9d2de2.8562f0ef.js
nonebot_plugin_docs/dist/assets/js/0ad5a17a.58b421f1.js
nonebot_plugin_docs/dist/assets/js/0c03e66c.81819880.js
nonebot_plugin_docs/dist/assets/js/0c287666.33b88bec.js
nonebot_plugin_docs/dist/assets/js/0c2a4ce2.869691a9.js
nonebot_plugin_docs/dist/assets/js/0cf64399.48cfa0ab.js
nonebot_plugin_docs/dist/assets/js/0ea3cbb2.df3ba00b.js
nonebot_plugin_docs/dist/assets/js/0fc90ea1.e148fa23.js
nonebot_plugin_docs/dist/assets/js/0fdeea60.d783dae5.js
nonebot_plugin_docs/dist/assets/js/0ff9ca52.92173a84.js
nonebot_plugin_docs/dist/assets/js/108073e2.3209730f.js
nonebot_plugin_docs/dist/assets/js/11e55d40.c32c6f54.js
nonebot_plugin_docs/dist/assets/js/1281.2f32f259.js
nonebot_plugin_docs/dist/assets/js/136548c8.d0f01e91.js
nonebot_plugin_docs/dist/assets/js/1468b7b1.88bebc0e.js
nonebot_plugin_docs/dist/assets/js/1479827a.ed01a389.js
nonebot_plugin_docs/dist/assets/js/1497044a.50eb6d05.js
nonebot_plugin_docs/dist/assets/js/14f5c6aa.68da147a.js
nonebot_plugin_docs/dist/assets/js/1546000d.3b2113ca.js
nonebot_plugin_docs/dist/docs/2.4.1/advanced/plugin-info/index.html
nonebot_plugin_docs/dist/docs/2.4.2/advanced/plugin-info/index.html
nonebot_plugin_docs/dist/docs/advanced/plugin-info/index.html
nonebot_plugin_docs/dist/docs/next/advanced/plugin-info/index.html
nonebot_plugin_docs-2.4.3.dist-info/WHEEL
nonebot_plugin_docs-2.4.3.dist-info/METADATA
nonebot_plugin_docs-2.4.3.dist-info/RECORD
