Metadata-Version: 2.4
Name: nonebot-plugin-docs
Version: 2.4.3
Summary: View NoneBot2 Docs Locally
Keywords: nonebot,nonebot2,docs
Author: yanyongyu
Author-email: yanyongyu <yyy@nonebot.dev>
License-Expression: MIT
Requires-Dist: nonebot2>=2.0.0,<3.0.0
Requires-Python: >=3.9, <4.0
Project-URL: Homepage, https://github.com/nonebot/nonebot2/blob/master/packages/nonebot-plugin-docs
Project-URL: Repository, https://github.com/nonebot/nonebot2
